webpos_sdk/__init__.py
webpos_sdk/api_context.py
webpos_sdk/client.py
webpos_sdk/common.py
webpos_sdk/actions/__init__.py
webpos_sdk/actions/client_credentials_login.py
webpos_sdk/actions/common.py
webpos_sdk/actions/create_payment_order.py
webpos_sdk/actions/delete_payment_order.py
webpos_sdk/actions/factory.py
webpos_sdk/actions/get_callbacks.py
webpos_sdk/actions/get_payment_order.py
webpos_sdk/actions/get_payment_orders.py
webpos_sdk/actions/get_web_pos_payments.py
webpos_sdk/actions/payment_reset.py
webpos_sdk/actions/payment_update.py
webpos_sdk/callbacks/__init__.py
webpos_sdk/callbacks/factory.py
webpos_sdk/callbacks/handler.py
webpos_sdk/exceptions/__init__.py
webpos_sdk/exceptions/common.py
webpos_sdk/exceptions/exceptions.py
webpos_sdk/lib/__init__.py
webpos_sdk/lib/cache.py
webpos_sdk/lib/constants.py
webpos_sdk/lib/hooks.py
webpos_sdk/objects/__init__.py
webpos_sdk/objects/callback.py
webpos_sdk/objects/callback_list.py
webpos_sdk/objects/callback_payment_order.py
webpos_sdk/objects/client_credentials.py
webpos_sdk/objects/client_credentials_login_response.py
webpos_sdk/objects/currency_retrieval.py
webpos_sdk/objects/deposit_account_lite.py
webpos_sdk/objects/out.py
webpos_sdk/objects/paid_status.py
webpos_sdk/objects/payment_cancelled.py
webpos_sdk/objects/payment_chargeback.py
webpos_sdk/objects/payment_completed.py
webpos_sdk/objects/payment_dispute_end.py
webpos_sdk/objects/payment_dispute_start.py
webpos_sdk/objects/payment_expired.py
webpos_sdk/objects/payment_order_creation.py
webpos_sdk/objects/payment_order_creation_response.py
webpos_sdk/objects/payment_order_creator.py
webpos_sdk/objects/payment_order_deletion_response.py
webpos_sdk/objects/payment_order_list.py
webpos_sdk/objects/payment_order_retrieval.py
webpos_sdk/objects/payment_order_state.py
webpos_sdk/objects/payment_overpaid.py
webpos_sdk/objects/payment_update_object.py
webpos_sdk/objects/rate_retrieval.py
webpos_sdk/objects/transaction.py
chainside_webpos_sdk-2.0.1.dist-info/METADATA
chainside_webpos_sdk-2.0.1.dist-info/WHEEL
chainside_webpos_sdk-2.0.1.dist-info/top_level.txt
chainside_webpos_sdk-2.0.1.dist-info/RECORD
